illallangi/django/data/__init__.py
illallangi/django/data/__version__.py
illallangi/django/data/apps.py
illallangi/django/data/asgi.py
illallangi/django/data/settings.py
illallangi/django/data/signals.py
illallangi/django/data/urls.py
illallangi/django/data/wsgi.py
illallangi/django/data/admin/__init__.py
illallangi/django/data/admin/model.py
illallangi/django/data/admin/synchronize.py
illallangi/django/data/management/__init__.py
illallangi/django/data/management/commands/__init__.py
illallangi/django/data/management/commands/synchronize.py
illallangi/django/data/migrations/0001_initial.py
illallangi/django/data/migrations/__init__.py
illallangi/django/data/models/__init__.py
illallangi/django/data/models/model.py
illallangi/django/data/models/synchronize.py
illallangi/django/data/templates/base.html
illallangi/django/data/templates/partial.html
illallangi/django/data/templates/table.html
illallangi/django/data/templates/home/home_list.html
illallangi/django/data/templatetags/__init__.py
illallangi/django/data/templatetags/home_breadcrumbs.py
illallangi/django/data/views/__init__.py
illallangi/django/data/views/favicon.py
illallangi/django/data/views/home_list.py
illallangi_django_data-0.2.0.dist-info/METADATA
illallangi_django_data-0.2.0.dist-info/WHEEL
illallangi_django_data-0.2.0.dist-info/licenses/LICENSE
illallangi_django_data-0.2.0.dist-info/RECORD
